<?xml version="1.0" encoding="utf-8" ?>
<Defs>

  <UINotIncluded.Widget.ExtendedWidgetDef>
    <defName>BlankSpace</defName>
  </UINotIncluded.Widget.ExtendedWidgetDef>

  <UINotIncluded.Widget.ExtendedWidgetDef>
    <defName>Weather</defName>
  </UINotIncluded.Widget.ExtendedWidgetDef>

  <UINotIncluded.Widget.ExtendedWidgetDef>
    <defName>Time</defName>
  </UINotIncluded.Widget.ExtendedWidgetDef>

  <UINotIncluded.Widget.ExtendedWidgetDef>
    <defName>TimeSpeed</defName>
  </UINotIncluded.Widget.ExtendedWidgetDef>

  <UINotIncluded.Widget.ExtendedWidgetDef>
    <defName>TimeIRL</defName>
  </UINotIncluded.Widget.ExtendedWidgetDef>

</Defs>